mssi/.ipynb_checkpoints/__init__-checkpoint.py
mssi/.ipynb_checkpoints/mssi-checkpoint.py
mssi/.ipynb_checkpoints/utils-checkpoint.py
mssi/__init__.py
mssi/mssi.py
mssi/utils.py
mssi-0.1.9.dist-info/LICENSE
mssi-0.1.9.dist-info/METADATA
mssi-0.1.9.dist-info/WHEEL
mssi-0.1.9.dist-info/RECORD
