Metadata-Version: 2.1
Name: mssi
Version: 0.1.9
Summary: Multiscale gene-gene correlation for spatial transcriptomics data
License: MIT
Author: Doron Haviv
Requires-Python: >=3.9,<4.0
Classifier: License :: OSI Approved :: MIT License
Classifier: Programming Language :: Python :: 3
Classifier: Programming Language :: Python :: 3.9
Classifier: Programming Language :: Python :: 3.10
Classifier: Programming Language :: Python :: 3.11
Classifier: Programming Language :: Python :: 3.12
Requires-Dist: pygsp
Requires-Dist: scipy (==1.11.0)
